{
  "match_time_s": 300,
  "time_bucket_s": 20,
  "lambda_0": 0.02,
  "k_fault": 3.0,
  "delta_H_pause": 0.2,
  "delta_H_reset": 0.1,
  "p_score_loss_per_step": 0.15,
  "tau_repair_buckets": 15,
  "tau_pause_buckets": 3,
  "tau_reset_buckets": 1,
  "base_win_scale": 1.0,
  "fall_down_weight": 0.35,
  "fault_time_weight": 0.4,
  "fault_action_weight": 0.3,
  "p_pause_score_loss": 0.03,
  "p_reset_score_loss": 0.08,
  "resource_uplift_scale": 1.0,
  "max_uplift_leading": 0.025,
  "max_uplift_tied": 0.16,
  "max_uplift_trailing": 0.18,
  "resource_time_mode": "opportunity_bucket",
  "max_reset": 2,
  "max_pause": 2,
  "max_repair": 1
}
